{
  "address": "2aBRNteWaNGAh3R79RWengDwzn8SnGVtYJeX4Wru6ejK",
  "metadata": {
    "name": "presale",
    "version": "0.1.0",
    "spec": "0.1.0",
    "description": "TokenPicks Presale Program"
  },
  "instructions": [
    {
      "name": "buy",
      "discriminator": [
        102,
        6,
        61,
        18,
        1,
        218,
        235,
        234
      ],
      "accounts": [
        {
          "name": "buyer",
          "writable": true,
          "signer": true
        },
        {
          "name": "beneficiary"
        },
        {
          "name": "presale",
          "writable": true
        },
        {
          "name": "token_mint"
        },
        {
          "name": "token_vault",
          "writable": true,
          "pda": {
            "seeds": [
              {
                "kind": "const",
                "value": [
                  118,
                  97,
                  117,
                  108,
                  116
                ]
              },
              {
                "kind": "account",
                "path": "presale"
              }
            ]
          }
        },
        {
          "name": "beneficiary_token",
          "writable": true,
          "pda": {
            "seeds": [
              {
                "kind": "account",
                "path": "beneficiary"
              },
              {
                "kind": "const",
                "value": [
                  6,
                  221,
                  246,
                  225,
                  215,
                  101,
                  161,
                  147,
                  217,
                  203,
                  225,
                  70,
                  206,
                  235,
                  121,
                  172,
                  28,
                  180,
                  133,
                  237,
                  95,
                  91,
                  55,
                  145,
                  58,
                  140,
                  245,
                  133,
                  126,
                  255,
                  0,
                  169
                ]
              },
              {
                "kind": "account",
                "path": "token_mint"
              }
            ],
            "program": {
              "kind": "const",
              "value": [
                140,
                151,
                37,
                143,
                78,
                36,
                137,
                241,
                187,
                61,
                16,
                41,
                20,
                142,
                13,
                131,
                11,
                90,
                19,
                153,
                218,
                255,
                16,
                132,
                4,
                142,
                123,
                216,
                219,
                233,
                248,
                89
              ]
            }
          }
        },
        {
          "name": "buyer_state",
          "writable": true,
          "pda": {
            "seeds": [
              {
                "kind": "const",
                "value": [
                  98,
                  117,
                  121,
                  101,
                  114
                ]
              },
              {
                "kind": "account",
                "path": "presale"
              },
              {
                "kind": "account",
                "path": "buyer"
              }
            ]
          }
        },
        {
          "name": "wallet",
          "writable": true
        },
        {
          "name": "token_program",
          "address": "TokenkegQfeZyiNwAJbNbGKPFXCWuBvf9Ss623VQ5DA"
        },
        {
          "name": "associated_token_program",
          "address": "ATokenGPvbdGVxr1b2hvZbsiqW5xWH25efTNsLJA8knL"
        },
        {
          "name": "system_program",
          "address": "11111111111111111111111111111111"
        }
      ],
      "args": [
        {
          "name": "lamports",
          "type": "u64"
        }
      ]
    },
    {
      "name": "close_sale",
      "discriminator": [
        124,
        201,
        1,
        146,
        231,
        103,
        193,
        152
      ],
      "accounts": [
        {
          "name": "owner",
          "signer": true,
          "relations": [
            "presale"
          ]
        },
        {
          "name": "presale",
          "writable": true
        }
      ],
      "args": []
    },
    {
      "name": "finalize_sale",
      "discriminator": [
        62,
        138,
        254,
        160,
        192,
        113,
        177,
        58
      ],
      "accounts": [
        {
          "name": "owner",
          "signer": true,
          "relations": [
            "presale"
          ]
        },
        {
          "name": "presale",
          "writable": true
        },
        {
          "name": "token_vault",
          "writable": true,
          "pda": {
            "seeds": [
              {
                "kind": "const",
                "value": [
                  118,
                  97,
                  117,
                  108,
                  116
                ]
              },
              {
                "kind": "account",
                "path": "presale"
              }
            ]
          }
        },
        {
          "name": "destination",
          "writable": true
        },
        {
          "name": "token_program",
          "address": "TokenkegQfeZyiNwAJbNbGKPFXCWuBvf9Ss623VQ5DA"
        }
      ],
      "args": []
    },
    {
      "name": "initialize",
      "discriminator": [
        175,
        175,
        109,
        31,
        13,
        152,
        155,
        237
      ],
      "accounts": [
        {
          "name": "owner",
          "writable": true,
          "signer": true
        },
        {
          "name": "token_mint"
        },
        {
          "name": "wallet"
        },
        {
          "name": "presale",
          "writable": true,
          "pda": {
            "seeds": [
              {
                "kind": "const",
                "value": [
                  112,
                  114,
                  101,
                  115,
                  97,
                  108,
                  101
                ]
              },
              {
                "kind": "account",
                "path": "owner"
              },
              {
                "kind": "account",
                "path": "token_mint"
              }
            ]
          }
        },
        {
          "name": "token_vault",
          "writable": true,
          "pda": {
            "seeds": [
              {
                "kind": "const",
                "value": [
                  118,
                  97,
                  117,
                  108,
                  116
                ]
              },
              {
                "kind": "account",
                "path": "presale"
              }
            ]
          }
        },
        {
          "name": "system_program",
          "address": "11111111111111111111111111111111"
        },
        {
          "name": "token_program",
          "address": "TokenkegQfeZyiNwAJbNbGKPFXCWuBvf9Ss623VQ5DA"
        },
        {
          "name": "rent",
          "address": "SysvarRent111111111111111111111111111111111"
        }
      ],
      "args": [
        {
          "name": "rate",
          "type": "u64"
        },
        {
          "name": "entrance_fee",
          "type": "u64"
        },
        {
          "name": "max_buy",
          "type": "u64"
        },
        {
          "name": "soft_cap",
          "type": "u64"
        },
        {
          "name": "hard_cap",
          "type": "u64"
        }
      ]
    },
    {
      "name": "open_sale",
      "discriminator": [
        246,
        220,
        152,
        93,
        31,
        43,
        199,
        143
      ],
      "accounts": [
        {
          "name": "owner",
          "signer": true,
          "relations": [
            "presale"
          ]
        },
        {
          "name": "presale",
          "writable": true
        },
        {
          "name": "token_vault",
          "pda": {
            "seeds": [
              {
                "kind": "const",
                "value": [
                  118,
                  97,
                  117,
                  108,
                  116
                ]
              },
              {
                "kind": "account",
                "path": "presale"
              }
            ]
          }
        }
      ],
      "args": []
    },
    {
      "name": "reopen_finalize_sale",
      "discriminator": [
        254,
        118,
        118,
        24,
        45,
        163,
        165,
        204
      ],
      "accounts": [
        {
          "name": "owner",
          "signer": true,
          "relations": [
            "presale"
          ]
        },
        {
          "name": "presale",
          "writable": true
        }
      ],
      "args": []
    },
    {
      "name": "set_entrance_fee",
      "discriminator": [
        52,
        182,
        213,
        144,
        83,
        243,
        107,
        23
      ],
      "accounts": [
        {
          "name": "owner",
          "signer": true,
          "relations": [
            "presale"
          ]
        },
        {
          "name": "presale",
          "writable": true
        }
      ],
      "args": [
        {
          "name": "entrance_fee",
          "type": "u64"
        }
      ]
    },
    {
      "name": "set_max_buy",
      "discriminator": [
        110,
        27,
        208,
        179,
        80,
        151,
        59,
        95
      ],
      "accounts": [
        {
          "name": "owner",
          "signer": true,
          "relations": [
            "presale"
          ]
        },
        {
          "name": "presale",
          "writable": true
        }
      ],
      "args": [
        {
          "name": "max_buy",
          "type": "u64"
        }
      ]
    },
    {
      "name": "set_rate",
      "discriminator": [
        99,
        58,
        170,
        238,
        160,
        120,
        74,
        11
      ],
      "accounts": [
        {
          "name": "owner",
          "signer": true,
          "relations": [
            "presale"
          ]
        },
        {
          "name": "presale",
          "writable": true
        }
      ],
      "args": [
        {
          "name": "rate",
          "type": "u64"
        }
      ]
    }
  ],
  "accounts": [
    {
      "name": "BuyerState",
      "discriminator": [
        196,
        226,
        50,
        172,
        9,
        123,
        201,
        250
      ]
    },
    {
      "name": "Presale",
      "discriminator": [
        38,
        215,
        222,
        14,
        115,
        220,
        52,
        168
      ]
    }
  ],
  "events": [
    {
      "name": "TokensPurchased",
      "discriminator": [
        214,
        119,
        105,
        186,
        114,
        205,
        228,
        181
      ]
    }
  ],
  "errors": [
    {
      "code": 6000,
      "name": "SaleClosed",
      "msg": "Sale is closed"
    },
    {
      "code": 6001,
      "name": "NoTokens",
      "msg": "No tokens available"
    },
    {
      "code": 6002,
      "name": "AmountTooLow",
      "msg": "Amount too low"
    },
    {
      "code": 6003,
      "name": "AmountTooHigh",
      "msg": "Amount too high"
    },
    {
      "code": 6004,
      "name": "InvalidAmount",
      "msg": "Invalid amount"
    },
    {
      "code": 6005,
      "name": "InvalidBeneficiary",
      "msg": "Invalid beneficiary"
    },
    {
      "code": 6006,
      "name": "InsufficientTokens",
      "msg": "Insufficient tokens in vault"
    },
    {
      "code": 6007,
      "name": "Overflow",
      "msg": "Math overflow"
    }
  ],
  "types": [
    {
      "name": "BuyerState",
      "type": {
        "kind": "struct",
        "fields": [
          {
            "name": "presale",
            "type": "pubkey"
          },
          {
            "name": "buyer",
            "type": "pubkey"
          },
          {
            "name": "contributed_lamports",
            "type": "u64"
          },
          {
            "name": "tokens_purchased",
            "type": "u64"
          },
          {
            "name": "bump",
            "type": "u8"
          }
        ]
      }
    },
    {
      "name": "Presale",
      "type": {
        "kind": "struct",
        "fields": [
          {
            "name": "owner",
            "type": "pubkey"
          },
          {
            "name": "token_mint",
            "type": "pubkey"
          },
          {
            "name": "token_vault",
            "type": "pubkey"
          },
          {
            "name": "wallet",
            "type": "pubkey"
          },
          {
            "name": "rate",
            "type": "u64"
          },
          {
            "name": "entrance_fee",
            "type": "u64"
          },
          {
            "name": "max_buy",
            "type": "u64"
          },
          {
            "name": "soft_cap",
            "type": "u64"
          },
          {
            "name": "hard_cap",
            "type": "u64"
          },
          {
            "name": "lamports_raised",
            "type": "u64"
          },
          {
            "name": "tokens_sold",
            "type": "u64"
          },
          {
            "name": "status_ico",
            "type": "bool"
          },
          {
            "name": "finalize_status",
            "type": "bool"
          },
          {
            "name": "bump",
            "type": "u8"
          }
        ]
      }
    },
    {
      "name": "TokensPurchased",
      "type": {
        "kind": "struct",
        "fields": [
          {
            "name": "purchaser",
            "type": "pubkey"
          },
          {
            "name": "beneficiary",
            "type": "pubkey"
          },
          {
            "name": "lamports",
            "type": "u64"
          },
          {
            "name": "amount",
            "type": "u64"
          }
        ]
      }
    }
  ]
}